awsstepfuncs/__init__.py
awsstepfuncs/_repo_version.py
awsstepfuncs/abstract_state.py
awsstepfuncs/json_path.py
awsstepfuncs/state.py
awsstepfuncs/state_machine.py
awsstepfuncs/types.py
awsstepfuncs/visualization.py
awsstepfuncs-0.0.1.dist-info/LICENSE
awsstepfuncs-0.0.1.dist-info/METADATA
awsstepfuncs-0.0.1.dist-info/WHEEL
awsstepfuncs-0.0.1.dist-info/top_level.txt
awsstepfuncs-0.0.1.dist-info/RECORD
